clifn/__init__.py
clifn/__main__.py
clifn-0.0.2.dist-info/METADATA
clifn-0.0.2.dist-info/WHEEL
clifn-0.0.2.dist-info/top_level.txt
clifn-0.0.2.dist-info/RECORD
