Metadata-Version: 2.1
Name: clifn
Version: 0.0.2
Summary: helper classes for organizing docopt programs
Home-page: https://github.com/tgbugs/pyontutils/tree/master/clifn
Author: Tom Gillespie
Author-email: tgbugs@gmail.com
License: MIT
Keywords: cli docopt
Classifier: Development Status :: 4 - Beta
Classifier: License :: OSI Approved :: MIT License
Classifier: Programming Language :: Python :: 3.7
Classifier: Programming Language :: Python :: 3.8
Classifier: Programming Language :: Python :: 3.9
Classifier: Programming Language :: Python :: 3.10
Classifier: Programming Language :: Python :: 3.11
Classifier: Programming Language :: Python :: 3.12
Classifier: Programming Language :: Python :: 3.13
Classifier: Programming Language :: Python :: Implementation :: CPython
Classifier: Programming Language :: Python :: Implementation :: PyPy
Classifier: Operating System :: POSIX :: Linux
Classifier: Operating System :: MacOS :: MacOS X
Classifier: Operating System :: Microsoft :: Windows
Requires-Python: >=3.7
Requires-Dist: docopt
Provides-Extra: dev
Requires-Dist: pytest-cov; extra == "dev"
Requires-Dist: wheel; extra == "dev"
Provides-Extra: test
Requires-Dist: pytest; extra == "test"
